wasm_tob/__init__.py
wasm_tob/__main__.py
wasm_tob/compat.py
wasm_tob/decode.py
wasm_tob/formatter.py
wasm_tob/immtypes.py
wasm_tob/modtypes.py
wasm_tob/opcodes.py
wasm_tob/types.py
wasm_tob/wasmtypes.py
wasm_tob-1.0.1.dist-info/entry_points.txt
wasm_tob-1.0.1.dist-info/LICENSE
wasm_tob-1.0.1.dist-info/WHEEL
wasm_tob-1.0.1.dist-info/METADATA
wasm_tob-1.0.1.dist-info/RECORD
