Metadata-Version: 2.1
Name: wasm-tob
Version: 1.0.1
Summary: WebAssembly decoder & disassembler
Keywords: wasm,disassembler,decoder
Author-email: Trail of Bits <opensource@trailofbits.com>
Requires-Python: >=3.7
Classifier: License :: OSI Approved :: MIT License
Classifier: Programming Language :: Python :: 3 :: Only
Classifier: Programming Language :: Python :: 3
Classifier: Programming Language :: Python :: 3.7
Classifier: Programming Language :: Python :: 3.8
Classifier: Programming Language :: Python :: 3.9
Classifier: Programming Language :: Python :: 3.10
Classifier: Programming Language :: Python :: 3.11
Classifier: Development Status :: 5 - Production/Stable
Classifier: Intended Audience :: Science/Research
Classifier: Intended Audience :: Developers
Classifier: Topic :: Security
Requires-Dist: build ; extra == "dev"
Project-URL: Homepage, https://pypi.org/project/wasm-tob/
Project-URL: Issues, https://github.com/trail-of-forks/wasm-tob/issues
Project-URL: Source, https://github.com/trail-of-forks/wasm-tob
Provides-Extra: dev
